imswitch/__init__.py
imswitch/__main__.py
imswitch/config.py
imswitch/_data/icon.ico
imswitch/_data/icon.png
imswitch/_data/openapi.json
imswitch/_data/images/12_well_plate.json
imswitch/_data/images/24_well_plate.json
imswitch/_data/images/4_slide_carrier.json
imswitch/_data/images/6_well_plate.json
imswitch/_data/images/96_well_plate.json
imswitch/_data/images/Development.json
imswitch/_data/images/Wellplate24.png
imswitch/_data/images/Wellplate32.json
imswitch/_data/images/Wellplate6.png
imswitch/_data/images/Wellplate96.json
imswitch/_data/images/WellplateAdapter3Slides.png
imswitch/_data/images/calculatewellplatepositions.py
imswitch/_data/images/histoASHLARStitch.jpg
imswitch/_data/images/slide carrier.png
imswitch/_data/images/slide carrier_828x662.png
imswitch/_data/images/slide carrier_876x730.png
imswitch/_data/images/slide carrier_876x730_transparent background.png
imswitch/_data/images/samplelayouts/12wellplate_1509x1010.png
imswitch/_data/images/samplelayouts/1536wellplate_1509x1010.png
imswitch/_data/images/samplelayouts/24wellplate_1509x1010.png
imswitch/_data/images/samplelayouts/384wellplate_1509x1010.png
imswitch/_data/images/samplelayouts/4slidecarrier_1509x1010.png
imswitch/_data/images/samplelayouts/6wellplate_1509x1010.png
imswitch/_data/images/samplelayouts/96wellplate_1509x1010.png
imswitch/_data/images/samplelayouts/generateWellplateJSON.py
imswitch/_data/libs/GPU_acc_recon.dll
imswitch/_data/libs/cudart64_90.dll
imswitch/_data/libs/opencv_core340.dll
imswitch/_data/libs/opencv_imgcodecs340.dll
imswitch/_data/libs/opencv_imgproc340.dll
imswitch/_data/ssl/cert.pem
imswitch/_data/ssl/key.pem
imswitch/_data/static/swagger-ui-bundle.js
imswitch/_data/static/swagger-ui.css
imswitch/_data/static/testwebsocket.html
imswitch/_data/static/imswitch/asset-manifest.json
imswitch/_data/static/imswitch/favicon.ico
imswitch/_data/static/imswitch/index.html
imswitch/_data/static/imswitch/logo192.png
imswitch/_data/static/imswitch/logo512.png
imswitchuc2-2.1.85.dist-info/licenses/LICENSE
imswitchuc2-2.1.85.dist-info/METADATA
imswitchuc2-2.1.85.dist-info/WHEEL
imswitchuc2-2.1.85.dist-info/entry_points.txt
imswitchuc2-2.1.85.dist-info/top_level.txt
imswitchuc2-2.1.85.dist-info/RECORD
