Metadata-Version: 2.4
Name: ImSwitchUC2
Version: 2.1.85
Summary: Microscopy control
Home-page: https://github.com/openuc2/ImSwitch
Author: Xavier Casas Moreno
Author-email: Benedict Diederich <benedictdied@gmail.com>
Maintainer-email: Benedict Diederich <benedictdied@gmail.com>
License: GPL-3.0-or-later
Project-URL: Homepage, https://github.com/openuc2/ImSwitch
Project-URL: Bug Tracker, https://github.com/openuc2/ImSwitch/issues
Classifier: Programming Language :: Python :: 3
Classifier: License :: OSI Approved :: GNU General Public License v3 or later (GPLv3+)
Classifier: Operating System :: OS Independent
Requires-Python: >=3.10
License-File: LICENSE
Requires-Dist: pydantic==2.11.4
Requires-Dist: coloredlogs>=15
Requires-Dist: colour-science>=0.3
Requires-Dist: dataclasses-json>=0.5
Requires-Dist: h5py>=2.10
Requires-Dist: pyvisa-py==0.4.1
Requires-Dist: lantzdev>=0.5.2
Requires-Dist: luddite>=1
Requires-Dist: nidaqmx>=0.5.7
Requires-Dist: numpy==2.1.2
Requires-Dist: packaging>=19
Requires-Dist: psutil>=5.4.8
Requires-Dist: pyserial>=3.4
Requires-Dist: requests>=2.25
Requires-Dist: scikit-image==0.25.2
Requires-Dist: Send2Trash>=1.8
Requires-Dist: tifffile>=2020.11.26
Requires-Dist: dask[complete]>=2024.8.0
Requires-Dist: fastAPI>=0.86.0
Requires-Dist: uvicorn[standard]>=0.19.0
Requires-Dist: matplotlib==3.9.2
Requires-Dist: opencv-python
Requires-Dist: dataclasses-json>=0.5
Requires-Dist: aiortc>=1.9.0
Requires-Dist: UC2-REST
Requires-Dist: tk>=0.1.0
Requires-Dist: jupyter
Requires-Dist: python-multipart>=0.0.5
Requires-Dist: piexif>=1.1.3
Requires-Dist: NanoImagingPack==2.1.4
Requires-Dist: imswitchclient>=0.1.2
Requires-Dist: psygnal
Requires-Dist: python-socketio[asyncio]==5.11.4
Requires-Dist: jupyterlab==4.2.5
Requires-Dist: python-dateutil>=2.8.1
Requires-Dist: zarr>=3.0.0
Requires-Dist: numcodecs>=0.13.1
Requires-Dist: aiohttp>=3.9.4
Requires-Dist: numba>=0.61.2
Provides-Extra: pyqt5
Requires-Dist: qtpy>=1.9; extra == "pyqt5"
Requires-Dist: PyQt5>=5.15.2; extra == "pyqt5"
Requires-Dist: QDarkStyle>=3; extra == "pyqt5"
Requires-Dist: QScintilla>=2.12; extra == "pyqt5"
Requires-Dist: PyQtWebEngine>=5.15.2; extra == "pyqt5"
Requires-Dist: pyqtgraph>=0.12.1; extra == "pyqt5"
Requires-Dist: napari[pyqt5]>=0.6.0; extra == "pyqt5"
Requires-Dist: lantzdev[qt]>=0.5.2; extra == "pyqt5"
Requires-Dist: qtpy>=1.9; extra == "pyqt5"
Provides-Extra: lepmont
Requires-Dist: smbus2; extra == "lepmont"
Requires-Dist: smbus; extra == "lepmont"
Requires-Dist: RPi.GPIO; extra == "lepmont"
Requires-Dist: luma.oled; extra == "lepmont"
Provides-Extra: ashlar
Requires-Dist: ashlarUC2; extra == "ashlar"
Provides-Extra: arkitekt
Requires-Dist: arkitekt==0.7.8; extra == "arkitekt"
Requires-Dist: arkitekt_next>=0.8.6; extra == "arkitekt"
Provides-Extra: imjoy
Requires-Dist: imjoy-rpc==0.5.59; extra == "imjoy"
Requires-Dist: imjoy_rpc; extra == "imjoy"
Requires-Dist: imjoy; extra == "imjoy"
Provides-Extra: dev
Requires-Dist: pytest; extra == "dev"
Dynamic: home-page
Dynamic: license-file
Dynamic: requires-python
